Workbook

Sheet README
A1: Sweet Cascade — Economy & Balance Workbook v1
A3: Date | B3: 2026-07-18
A4: Status | B4: MVP economy = stars only (by design). Brewing = Phase 2 DRAFT scaffold. Monetization = NOT DESIGNED (founder guardrail).
A5: Scope | B5: Consolidates every approved balance number: scoring constants (scoring-stars.md), 10 MVP levels (playable slice config, framework-derived), star/region-gate economy (world-map.md), Phase 2 brewing constraints (special-candies.md §9 + cross-GDD review).
A6: Legend | B6: BLUE text = hardcoded input/lever (edit these) · black = formula (do not overwrite) · YELLOW fill = key assumption or TO-BE-DESIGNED placeholder
A7: Sources | B7: design/gdd/scoring-stars.md · design/gdd/level-data-format.md · design/gdd/world-map.md · design/gdd/special-candies.md · prototypes/playable-slice/index.html (level table) · design/gdd/reviews/all-gdds-review-2026-07-18.md
A8: Rule | B8: Values here MIRROR the GDDs. The GDD is authoritative — a change here must propagate via /propagate-design-change, never silently.
A9: Verification | B9: Formulas verified 2026-07-18 by an independent Python mirror (74/74 formula cells: inputs vs GDD sources, formula strings, half-away-from-zero ROUND results). LibreOffice recalc was unavailable in the build container, so cached values are absent until first open — Excel/Sheets computes them automatically.

Sheet Scoring Constants
A1: Scoring Constants (scoring-stars.md, Reviewed–APPROVED)
A3: Constant | B3: Value | C3: Source / note
A4: TILE_BASE_VALUE (pts per cleared piece) | B4: 20 | C4: scoring-stars.md Formula 2; prototype-validated
A5: Chain multiplier | B5: linear = chain_index (uncapped) | C5: Formula 2; bounded by MAX_CASCADE_DEPTH
A6: Activation bonus — Striped (per piece) | B6: 60 | C6: Formula 3 (= 3 × TILE_BASE_VALUE)
A7: Activation bonus — Color Bomb (per piece) | B7: 180 | C7: Formula 3 (= 9 × TILE_BASE_VALUE)
A8: MAX_CASCADE_DEPTH | B8: 20 | C8: board-engine.md (inherited, sole owner)
A9: Star fraction — 1★ | B9: 0.625 | C9: Formula 6
A10: Star fraction — 2★ | B10: 0.8 | C10: Formula 6
A11: Star fraction — 3★ | B11: 0.975 | C11: Formula 6
A13: Derived combo pricing (per-piece bonus sums — no lookup table by design)
A14: Combo | B14: Price (pts, chain ×1) | C14: Derivation
A15: Bomb + regular color | B15: =B7 | C15: one bomb consumed
A16: Bomb + Striped | B16: =B7+B6 | C16: bomb + stripe consumed
A17: Bomb + Bomb | B17: =2*B7 | C17: two bombs consumed
A18: Striped + Striped | B18: =2*B6 | C18: two stripes consumed
A20: REFERENCE_SCORE_PER_MOVE(K) — function of color-pool size (Formula 4)
A21: color_pool size K | B21: RSPM (pts/move) | C21: Note
A22: 3 | B22: 255 | C22: heuristic ratio; recalibrate at Vertical Slice
A23: 4 | B23: 185 | C23: heuristic ratio
A24: 5 | B24: 160 | C24: empirical anchor: greedy bot 3,960 / 25 moves

Sheet Level Balance
A1: 10 MVP Levels (authored in playable slice; thresholds framework-derived, rounded)
A3: # | B3: level_id | C3: board | D3: pool K | E3: moves | F3: objective | G3: target | H3: auth 1★ | I3: auth 2★ | J3: auth 3★ | K3: RSPM(K) | L3: ref_max | M3: fw 1★ | N3: fw 2★ | O3: fw 3★ | P3: 1★ delta | Q3: difficulty beat
A4: 1 | B4: ck-001 | C4: 8×8 | D4: 4 | E4: 20 | F4: score | G4: 1800 | H4: 2300 | I4: 2950 | J4: 3600 | K4: =INDEX('Scoring Constants'!$B$22:$B$24,MATCH(D4,'Scoring Constants'!$A$22:$A$24,0)) | L4: =E4*K4 | M4: =ROUND(L4*'Scoring Constants'!$B$9,0) | N4: =ROUND(L4*'Scoring Constants'!$B$10,0) | O4: =ROUND(L4*'Scoring Constants'!$B$11,0) | P4: =H4-M4 | Q4: easy (teach)
A5: 2 | B5: ck-002 | C5: 8×8 | D5: 5 | E5: 22 | F5: score | G5: 2000 | H5: 2200 | I5: 2800 | J5: 3450 | K5: =INDEX('Scoring Constants'!$B$22:$B$24,MATCH(D5,'Scoring Constants'!$A$22:$A$24,0)) | L5: =E5*K5 | M5: =ROUND(L5*'Scoring Constants'!$B$9,0) | N5: =ROUND(L5*'Scoring Constants'!$B$10,0) | O5: =ROUND(L5*'Scoring Constants'!$B$11,0) | P5: =H5-M5 | Q5: easy-med
A6: 3 | B6: ck-003 | C6: 8×8 | D6: 5 | E6: 20 | F6: collect 40 strawberry | H6: 2000 | I6: 2550 | J6: 3100 | K6: =INDEX('Scoring Constants'!$B$22:$B$24,MATCH(D6,'Scoring Constants'!$A$22:$A$24,0)) | L6: =E6*K6 | M6: =ROUND(L6*'Scoring Constants'!$B$9,0) | N6: =ROUND(L6*'Scoring Constants'!$B$10,0) | O6: =ROUND(L6*'Scoring Constants'!$B$11,0) | P6: =H6-M6 | Q6: med (new type)
A7: 4 | B7: ck-004 | C7: 7×7 | D7: 5 | E7: 20 | F7: score | G7: 2000 | H7: 2000 | I7: 2550 | J7: 3100 | K7: =INDEX('Scoring Constants'!$B$22:$B$24,MATCH(D7,'Scoring Constants'!$A$22:$A$24,0)) | L7: =E7*K7 | M7: =ROUND(L7*'Scoring Constants'!$B$9,0) | N7: =ROUND(L7*'Scoring Constants'!$B$10,0) | O7: =ROUND(L7*'Scoring Constants'!$B$11,0) | P7: =H7-M7 | Q7: med-hard (small board)
A8: 5 | B8: ck-005 | C8: 8×8 | D8: 5 | E8: 18 | F8: collect 30 grape + score | G8: 1800 | H8: 1800 | I8: 2300 | J8: 2800 | K8: =INDEX('Scoring Constants'!$B$22:$B$24,MATCH(D8,'Scoring Constants'!$A$22:$A$24,0)) | L8: =E8*K8 | M8: =ROUND(L8*'Scoring Constants'!$B$9,0) | N8: =ROUND(L8*'Scoring Constants'!$B$10,0) | O8: =ROUND(L8*'Scoring Constants'!$B$11,0) | P8: =H8-M8 | Q8: hard (AND)
A9: 6 | B9: ck-006 | C9: 8×8 | D9: 4 | E9: 20 | F9: score | G9: 2300 | H9: 2300 | I9: 2950 | J9: 3600 | K9: =INDEX('Scoring Constants'!$B$22:$B$24,MATCH(D9,'Scoring Constants'!$A$22:$A$24,0)) | L9: =E9*K9 | M9: =ROUND(L9*'Scoring Constants'!$B$9,0) | N9: =ROUND(L9*'Scoring Constants'!$B$10,0) | O9: =ROUND(L9*'Scoring Constants'!$B$11,0) | P9: =H9-M9 | Q9: cooldown
A10: 7 | B10: ck-007 | C10: 8×8 masked | D10: 5 | E10: 22 | F10: collect 45 apple | H10: 2200 | I10: 2800 | J10: 3450 | K10: =INDEX('Scoring Constants'!$B$22:$B$24,MATCH(D10,'Scoring Constants'!$A$22:$A$24,0)) | L10: =E10*K10 | M10: =ROUND(L10*'Scoring Constants'!$B$9,0) | N10: =ROUND(L10*'Scoring Constants'!$B$10,0) | O10: =ROUND(L10*'Scoring Constants'!$B$11,0) | P10: =H10-M10 | Q10: med (shaped)
A11: 8 | B11: ck-008 | C11: 8×8 | D11: 5 | E11: 16 | F11: score | G11: 1600 | H11: 1600 | I11: 2050 | J11: 2500 | K11: =INDEX('Scoring Constants'!$B$22:$B$24,MATCH(D11,'Scoring Constants'!$A$22:$A$24,0)) | L11: =E11*K11 | M11: =ROUND(L11*'Scoring Constants'!$B$9,0) | N11: =ROUND(L11*'Scoring Constants'!$B$10,0) | O11: =ROUND(L11*'Scoring Constants'!$B$11,0) | P11: =H11-M11 | Q11: hard (tight moves)
A12: 9 | B12: ck-009 | C12: 9×9 | D12: 5 | E12: 24 | F12: collect 40 lemon + 40 citrus | H12: 2400 | I12: 3050 | J12: 3750 | K12: =INDEX('Scoring Constants'!$B$22:$B$24,MATCH(D12,'Scoring Constants'!$A$22:$A$24,0)) | L12: =E12*K12 | M12: =ROUND(L12*'Scoring Constants'!$B$9,0) | N12: =ROUND(L12*'Scoring Constants'!$B$10,0) | O12: =ROUND(L12*'Scoring Constants'!$B$11,0) | P12: =H12-M12 | Q12: hard+ (dual collect)
A13: 10 | B13: ck-010 | C13: 8×8 | D13: 5 | E13: 25 | F13: score | G13: 3200 | H13: 2500 | I13: 3200 | J13: 3900 | K13: =INDEX('Scoring Constants'!$B$22:$B$24,MATCH(D13,'Scoring Constants'!$A$22:$A$24,0)) | L13: =E13*K13 | M13: =ROUND(L13*'Scoring Constants'!$B$9,0) | N13: =ROUND(L13*'Scoring Constants'!$B$10,0) | O13: =ROUND(L13*'Scoring Constants'!$B$11,0) | P13: =H13-M13 | Q13: finale
A15: Deltas ≠ 0 = deliberate rounding to friendly numbers. Objective target < authored 1★ on teach levels is intentional (win floor = 1★). L1/L2 targets softened from greedy-bot data (2026-07-18 balance pass).

Sheet Star Economy
A1: Star Economy (world-map.md — stars are the ONLY progression currency at MVP)
A3: REGION_GATE_PERCENT | B3: 0.6 | C3: world-map.md Formula 1 lever
A4: Stars per level (max) | B4: 3
A5: Levels per region (launch) | B5: 30
A6: Levels per region (MVP cut) | B6: 10
A8: Region | B8: Gate (stars required) | C8: Max stars available before it | D8: Note
A9: 1 — Candy Kingdom Hub | B9: =ROUND($B$3*C9,0) | C9: =(1-1)*$B$4*$B$5 | D9: inert at MVP (single region)
A10: 2 — Frosted Peak | B10: =ROUND($B$3*C10,0) | C10: =(2-1)*$B$4*$B$5 | D10: reachable at ~2★ average — no 3★ grinding (review-verified)
A11: 3 — Sundrop Grove | B11: =ROUND($B$3*C11,0) | C11: =(3-1)*$B$4*$B$5 | D11: reachable at ~2★ average — no 3★ grinding (review-verified)
A12: 4 — Thistleberry Hollow | B12: =ROUND($B$3*C12,0) | C12: =(4-1)*$B$4*$B$5 | D12: reachable at ~2★ average — no 3★ grinding (review-verified)
A14: Max obtainable: MVP | B14: =B4*B6
A15: Max obtainable: launch (4 regions) | B15: =4*B4*B5

Sheet Brewing P2 DRAFT
A1: Booster Brewing Economy — Phase 2 SCAFFOLD (hook approved 2026-07-17; GDD gated on friction prototype)
A3: BINDING CONSTRAINTS (special-candies.md §9 + cross-GDD review 2026-07-18): (1) ingredient yield MUST be capped or diminishing — NEVER 1:1 of cleared_pieces (one Bomb+Bomb reports 64 cells → unbounded faucet); (2) brewing must FEED the star loop, never compete as a second progression currency; (3) harvest reads match_cleared per-color tallies only (no new board hooks).
A5: Ingredient | B5: Lore region (narrative doc) | C5: Harvest source (colors) | D5: Yield rule | E5: Sink (recipes) | F5: Status
A6: Berry juice | B6: Thistleberry Hollow | C6: strawberry + grape tallies | D6: TO BE DESIGNED (capped/curve) | E6: TO BE DESIGNED | F6: awaiting booster-brewing.md
A7: Citrus zest | B7: Sundrop Grove | C7: citrus + lemon tallies | D7: TO BE DESIGNED (capped/curve) | E7: TO BE DESIGNED | F7: awaiting booster-brewing.md
A8: Mint frost | B8: Frosted Peak | C8: apple tallies (proposed) | D8: TO BE DESIGNED (capped/curve) | E8: TO BE DESIGNED | F8: awaiting booster-brewing.md
A10: Ingredient↔region mapping is the narrative doc's optional lore thread — confirm with game-designer/economy-designer at Phase 2 authoring.

Sheet Monetization DIRECTION
A1: Monetization — DIRECTION CHOSEN (founder, 2026-07-18): consumable boosters (IAP) + rewarded-ads hybrid, COMBINED. Detailed design remains Phase 2, gated on co-design with booster-brewing.md (earned loop stays primary).
A3: Binding guardrails (game-concept.md anti-pillars): NEVER sell guaranteed level completion (pay-to-win kills Pillar 2); no currency UI shipped (coins/gems in the concept render were EXCLUDED); no lives/energy at MVP; social never punishes or spams. Scoping monetization is a founder decision — the options below are descriptive, not recommendations.
A5: Model | B5: What players buy | C5: Design cost before shipping | D5: Pillar risk | E5: Genre precedent | F5: Founder decision (2026-07-18)
A6: Cosmetic-only | B6: Fruit skins, board themes, Fizz outfits, trail FX | C6: Cosmetics pipeline + shop UI + owned-items save schema | D6: Lowest — zero gameplay impact | E6: Rare in match-3; common elsewhere | F6: NOT selected (may return later as add-on)
A7: Consumable boosters | B7: Pre-level boosters / extra moves | C7: Must reconcile with the EARNED brewing loop (Phase 2) or it undercuts the hook; pricing + pity design | D7: Medium — extra moves flirt with pay-for-completion | E7: Candy Crush / Royal Match core model | F7: SELECTED — Phase 2 design, must reconcile with earned brewing loop
A8: Season pass | B8: Cosmetic + booster reward track per season | C8: Events engine (Phase 3) prerequisite; season content cadence | D8: Low-medium if cosmetic-leaning | E8: Royal Match, most modern match-3 | F8: NOT selected (needs events engine, Phase 3 — revisit then)
A9: Ad-supported hybrid | B9: Optional rewarded ads (booster / retry) | C9: Ad mediation SDK + placement design + UX guardrails | D9: Medium — session-flow interruption risk | E9: Common in casual | F9: SELECTED — Phase 2 design, placement UX + mediation SDK (future ADR)
A11: Binding follow-ups: (1) booster-brewing.md (Phase 2) and the monetization GDD are ONE design task — paid boosters must never obsolete brewed ones; (2) rewarded-ad placements need UX-review sign-off (session-flow guardrail); (3) ad-mediation SDK choice = future ADR; (4) anti-pillars unchanged: no guaranteed-completion sales, no pay-to-win stars.
